k8062/__init__.py
k8062/__main__.py
k8062/k8062.py
k8062/libs/32/FASTTime32.dll
k8062/libs/32/K8062D.dll
k8062/libs/32/K8062e.exe
k8062/libs/64/FASTTime32.dll
k8062/libs/64/K8062D.dll
k8062/libs/64/K8062e.exe
k8062-0.1.2.dist-info/LICENSE.txt
k8062-0.1.2.dist-info/METADATA
k8062-0.1.2.dist-info/WHEEL
k8062-0.1.2.dist-info/entry_points.txt
k8062-0.1.2.dist-info/top_level.txt
k8062-0.1.2.dist-info/RECORD
