Metadata-Version: 2.1
Name: k8062
Version: 0.1.2
Summary: Python Wrapper for the Velleman k8062 DMX controller
Home-page: https://github.com/TheTripleV/k8062
Author: TheTripleV
License: MIT
Platform: UNKNOWN
Classifier: License :: OSI Approved :: MIT License
Classifier: Operating System :: Microsoft :: Windows
